edu_async_tasks/__init__.py
edu_async_tasks/config.py
edu_async_tasks/core/__init__.py
edu_async_tasks/core/apps.py
edu_async_tasks/core/models.py
edu_async_tasks/core/services.py
edu_async_tasks/core/tasks.py
edu_async_tasks/core/adapters/__init__.py
edu_async_tasks/core/adapters/db.py
edu_async_tasks/core/domain/__init__.py
edu_async_tasks/core/domain/model.py
edu_async_tasks/core/migrations/0001_initial.py
edu_async_tasks/core/migrations/0002_task_type_and_status_data.py
edu_async_tasks/core/migrations/0003_alter_runningtask_profile_id.py
edu_async_tasks/core/migrations/0004_runningtask_organization_id.py
edu_async_tasks/core/migrations/__init__.py
edu_async_tasks/rest/__init__.py
edu_async_tasks/rest/apps.py
edu_async_tasks/rest/urls.py
edu_async_tasks/rest/async_task_statuses/__init__.py
edu_async_tasks/rest/async_task_statuses/serializers.py
edu_async_tasks/rest/async_task_statuses/urls.py
edu_async_tasks/rest/async_task_statuses/views.py
edu_async_tasks/rest/async_task_types/__init__.py
edu_async_tasks/rest/async_task_types/serializers.py
edu_async_tasks/rest/async_task_types/urls.py
edu_async_tasks/rest/async_task_types/views.py
edu_async_tasks/rest/running_tasks/__init__.py
edu_async_tasks/rest/running_tasks/filters.py
edu_async_tasks/rest/running_tasks/serializers.py
edu_async_tasks/rest/running_tasks/urls.py
edu_async_tasks/rest/running_tasks/views.py
edu_async_tasks/rest/utils/__init__.py
edu_async_tasks/rest/utils/bootstrap.py
edu_async_tasks/rest/utils/pagination.py
testapp/__init__.py
testapp/manage.py
testapp/settings.py
testapp/urls.py
testapp/app/__init__.py
testapp/app/apps.py
testapp/app/tasks.py
testapp/app/tests/__init__.py
testapp/app/tests/test_config.py
testapp/app/tests/test_rest.py
testapp/app/tests/test_tasks.py
testapp/entrypoints/__init__.py
testapp/entrypoints/asgi.py
testapp/entrypoints/celery.py
testapp/entrypoints/wsgi.py
testapp/persons/__init__.py
testapp/persons/models.py
testapp/persons/migrations/0001_initial.py
edu_async_tasks-2.3.1.dist-info/METADATA
edu_async_tasks-2.3.1.dist-info/WHEEL
edu_async_tasks-2.3.1.dist-info/top_level.txt
edu_async_tasks-2.3.1.dist-info/RECORD
