Metadata-Version: 2.4
Name: edu-async-tasks
Version: 2.3.1
Summary: Пакет "Реестра "Асинхронных задач"
Author-email: "АО \"БАРС Груп\"" <education_dev@bars-open.ru>
Classifier: Intended Audience :: Developers
Classifier: Environment :: Web Environment
Classifier: Natural Language :: Russian
Classifier: Operating System :: OS Independent
Classifier: Development Status :: 5 - Production/Stable
Classifier: Programming Language :: Python :: 3.9
Classifier: Programming Language :: Python :: 3.10
Classifier: Programming Language :: Python :: 3.11
Classifier: Programming Language :: Python :: 3.12
Classifier: Framework :: Django :: 3.2
Classifier: Framework :: Django :: 4.0
Classifier: Framework :: Django :: 4.1
Classifier: Framework :: Django :: 4.2
Classifier: Framework :: Django :: 5.0
Requires-Python: >=3.9
Requires-Dist: setuptools; python_version >= "3.12"
Requires-Dist: Django<5.1,>=3.2
Requires-Dist: pydantic<2
Requires-Dist: djangorestframework==3.14.0
Requires-Dist: django_filter==23.3
Requires-Dist: celery[redis]>=5.3.5
Requires-Dist: m3-django-compatibility<2.0,>=1.12.0
Requires-Dist: m3-db-utils>=0.8.0
